iocare/__init__.py
iocare/iocareapi.py
iocare/devices/__init__.py
iocare/devices/purifier.py
python_iocare-0.1.5.dist-info/LICENSE
python_iocare-0.1.5.dist-info/METADATA
python_iocare-0.1.5.dist-info/WHEEL
python_iocare-0.1.5.dist-info/top_level.txt
python_iocare-0.1.5.dist-info/RECORD
