Metadata-Version: 2.1
Name: python-iocare
Version: 0.1.5
Summary: A Python library for the IOCare API utilized by Coway air purifiers
Home-page: UNKNOWN
Author: Evan Coleman
Author-email: oss@edc.me
License: UNKNOWN
Platform: UNKNOWN
Classifier: Programming Language :: Python :: 3
Classifier: License :: OSI Approved :: MIT License
Classifier: Operating System :: OS Independent
